<?xml version="1.0" encoding="UTF-8"?>
<beans xmlns="http://www.springframework.org/schema/beans"
       xmlns:xsi="http://www.w3.org/2001/XMLSchema-instance" xmlns:tx="http://www.springframework.org/schema/tx"
       xsi:schemaLocation="http://www.springframework.org/schema/beans http://www.springframework.org/schema/beans/spring-beans.xsd http://www.springframework.org/schema/tx http://www.springframework.org/schema/tx/spring-tx.xsd">


    <!-- ===== Managers statement ===== -->

    <bean id="abstractManager" class="org.nico.business.impl.AbstractManager" abstract="true">
        <property name="daoFactory" ref="daoFactory"/>
    </bean>

    <bean id="userManager" class="org.nico.business.impl.manager.UserManagerImpl" parent="abstractManager"/>
    <bean id="climbingSiteManager" class="org.nico.business.impl.manager.ClimbingSiteManagerImpl" parent="abstractManager"/>
    <bean id="photoManager" class="org.nico.business.impl.manager.PhotoManagerImpl" parent="abstractManager"/>
    <bean id="sectorManager" class="org.nico.business.impl.manager.SectorManagerImpl" parent="abstractManager"/>
    <bean id="routeManager" class="org.nico.business.impl.manager.RouteManagerImpl" parent="abstractManager"/>
    <bean id="commentManager" class="org.nico.business.impl.manager.CommentManagerImpl" parent="abstractManager"/>

    <bean id="enumManager" class="org.nico.business.impl.manager.EnumManagerImpl"></bean>
    <bean id="searchFilter" class="org.nico.business.impl.SearchFilter"></bean>

    <!-- ===== Manager Factory ===== -->
    <bean id="managerFactory" class="org.nico.business.impl.ManagerFactoryImpl">
        <property name="userManager" ref="userManager"/>
        <property name="climbingSiteManager" ref="climbingSiteManager"/>
        <property name="photoManager" ref="photoManager"/>
        <property name="sectorManager" ref="SectorManager"/>
        <property name="routeManager" ref="RouteManager"/>
    </bean>

    <!-- Transaction manager -->
    <tx:annotation-driven transaction-manager="txManagerEscalade" />
    <bean id="txManagerEscalade" class="org.springframework.jdbc.datasource.DataSourceTransactionManager">
        <property name="dataSource" ref="dataSourceEscalade"/>
    </bean>

    <!-- Encoder -->
    <bean id="encoder" class="org.nico.business.impl.manager.PasswordManagerImpl"></bean>

</beans>

